<?xml version="1.0"?>
<!DOCTYPE hibernate-mapping PUBLIC "-//Hibernate/Hibernate Mapping DTD 3.0//EN"
"http://hibernate.sourceforge.net/hibernate-mapping-3.0.dtd">
<!-- Generated 15/01/2020 14:07:16 by Hibernate Tools 3.5.0.Final -->
<hibernate-mapping>
    <class name="com.emprestimoapi.model.entidade.EnderecoContatoCliente" table="ENDERECOCONTATOCLIENTE">
        <id name="endereco" type="java.lang.String">
            <column name="ENDERECO" />
            <generator class="assigned" />
        </id>
        <property name="contato" type="java.lang.String">
            <column name="CONTATO" />
        </property>
    </class>
</hibernate-mapping>
